{
    "model": "ling-1t",
    "schedule": "zb_v",
    "disturbance": "both",
    "num_seeds": 20,
    "seed_base": 0,
    "candidate_top_k": 30,
    "candidate_mfu_window": 0.1,
    "full_seed_eval": false,
    "gbs_target": 256,
    "max_world": 4096,
    "n_phase_a_candidates": 81,
    "n_phase_a_shortlist": 4,
    "nominal_best_mfu": 0.0572679639252656,
    "git_rev": "b0424215bd4dea5ce8f55e488afd0e96ef0b921f",
    "candidates": [
        {
            "combo": {
                "tp": 2,
                "pp": 12,
                "ep": 16,
                "dp": 16,
                "mbn": 16,
                "mbs": 1,
                "etp": 1,
                "world_size": 384,
                "gbs_eff": 256,
                "recompute_family": "full_block",
                "recompute_layer_num_nominal": 7,
                "selective_flags": null
            },
            "nominal_mfu": 0.0572679639252656,
            "nominal_peak_mem_gb": 70.7059,
            "n_seeds_attempted": 20,
            "n_seeds_evaluated": 4,
            "early_exit": true,
            "fits_all_seeds": false,
            "failed_at_seed": 3,
            "peak_mem_at_failure_gb": null,
            "n_seeds_failed_memory": 1,
            "mfu_mean": 0.036278762968737076,
            "mfu_std": 0.0034850793432066453,
            "mfu_min": 0.033002552096342126,
            "mfu_max": 0.03994062969721843,
            "peak_mem_mean_gb": 72.24013333333333,
            "peak_mem_std_gb": 0.6213828959130856,
            "peak_mem_max_gb": 72.9345,
            "recompute_layer_num_max": 7
        },
        {
            "combo": {
                "tp": 2,
                "pp": 16,
                "ep": 16,
                "dp": 16,
                "mbn": 16,
                "mbs": 1,
                "etp": 1,
                "world_size": 512,
                "gbs_eff": 256,
                "recompute_family": "full_block",
                "recompute_layer_num_nominal": 3,
                "selective_flags": null
            },
            "nominal_mfu": 0.056467664894754264,
            "nominal_peak_mem_gb": 72.0708,
            "n_seeds_attempted": 20,
            "n_seeds_evaluated": 20,
            "early_exit": true,
            "fits_all_seeds": true,
            "mfu_mean": 0.033432202499042316,
            "mfu_std": 0.004429489792016668,
            "mfu_min": 0.02650078850973974,
            "mfu_max": 0.04213296266192666,
            "peak_mem_mean_gb": 66.54709,
            "peak_mem_std_gb": 2.788158254569907,
            "peak_mem_max_gb": 71.3118,
            "recompute_layer_num_max": 4
        },
        {
            "combo": {
                "tp": 2,
                "pp": 4,
                "ep": 64,
                "dp": 64,
                "mbn": 4,
                "mbs": 1,
                "etp": 1,
                "world_size": 512,
                "gbs_eff": 256,
                "recompute_family": "full_block",
                "recompute_layer_num_nominal": 15,
                "selective_flags": null
            },
            "nominal_mfu": 0.05547511184388544,
            "nominal_peak_mem_gb": 72.9365,
            "n_seeds_attempted": 20,
            "n_seeds_evaluated": 20,
            "early_exit": true,
            "fits_all_seeds": true,
            "mfu_mean": 0.05817795667553345,
            "mfu_std": 0.02349247552663615,
            "mfu_min": 0.036790532029117314,
            "mfu_max": 0.12937233640302093,
            "peak_mem_mean_gb": 72.548685,
            "peak_mem_std_gb": 1.0203052558064754,
            "peak_mem_max_gb": 73.902,
            "recompute_layer_num_max": 18
        },
        {
            "combo": {
                "tp": 2,
                "pp": 8,
                "ep": 32,
                "dp": 32,
                "mbn": 8,
                "mbs": 1,
                "etp": 1,
                "world_size": 512,
                "gbs_eff": 256,
                "recompute_family": "full_block",
                "recompute_layer_num_nominal": 7,
                "selective_flags": null
            },
            "nominal_mfu": 0.055238637326332746,
            "nominal_peak_mem_gb": 69.7178,
            "n_seeds_attempted": 20,
            "n_seeds_evaluated": 20,
            "early_exit": true,
            "fits_all_seeds": true,
            "mfu_mean": 0.04103003012821396,
            "mfu_std": 0.00829252183665959,
            "mfu_min": 0.0276243620941468,
            "mfu_max": 0.05716506721661851,
            "peak_mem_mean_gb": 70.842195,
            "peak_mem_std_gb": 2.3451474756622996,
            "peak_mem_max_gb": 73.5606,
            "recompute_layer_num_max": 9
        }
    ],
    "selected": {
        "combo": {
            "tp": 2,
            "pp": 4,
            "ep": 64,
            "dp": 64,
            "mbn": 4,
            "mbs": 1,
            "etp": 1,
            "world_size": 512,
            "gbs_eff": 256,
            "recompute_family": "full_block",
            "recompute_layer_num_nominal": 15,
            "selective_flags": null
        },
        "mfu_mean": 0.05817795667553345,
        "mfu_std": 0.02349247552663615,
        "peak_mem_mean_gb": 72.548685,
        "peak_mem_max_gb": 73.902,
        "recompute_layer_num_max": 18
    }
}